tdstone2/__init__.py
tdstone2/data_distribution.py
tdstone2/dataset_generation.py
tdstone2/tdscode.py
tdstone2/tdsfeature_engineering.py
tdstone2/tdsgenai.py
tdstone2/tdsgenai_lake.py
tdstone2/tdsgenai_seq2seq.py
tdstone2/tdshypermodel.py
tdstone2/tdsmapper.py
tdstone2/tdsmodel.py
tdstone2/tdstone.py
tdstone2/utils.py
tdstone2/data/tds_feature_engineering.py
tdstone2/data/tds_feature_engineering_jsonoutput.py
tdstone2/data/tds_feature_engineering_reducer.py
tdstone2/data/tds_scoring.py
tdstone2/data/tds_scoring_old.py
tdstone2/data/tds_seq2seq.py
tdstone2/data/tds_training.py
tdstone2/data/tds_training_old.py
tdstone2/data/tds_vector_embedding.py
tdstone2/data/tds_vector_embedding_batch.py
tdstone2/data/tds_vector_embedding_lake.py
tdstone2/data/tds_vector_embedding_old.py
tdstone2/feature_engineering_maker/__init__.py
tdstone2/feature_engineering_maker/python_script.py
tdstone2/model_maker/__init__.py
tdstone2/model_maker/feature_engineering.py
tdstone2/model_maker/scikit_learn.py
tdstone2-0.1.8.2.dist-info/METADATA
tdstone2-0.1.8.2.dist-info/WHEEL
tdstone2-0.1.8.2.dist-info/top_level.txt
tdstone2-0.1.8.2.dist-info/RECORD
