Metadata-Version: 2.1
Name: tdstone2
Version: 0.1.8.2
Summary: A package for Script Table Operator that applies set theory to machine learning in Python.
Author: Denis Molin
Requires-Python: >=3.6
Requires-Dist: teradataml>=17.20
Requires-Dist: pandas
Requires-Dist: numpy
Requires-Dist: sqlparse
Requires-Dist: torch
Requires-Dist: plotly
Requires-Dist: transformers
Requires-Dist: sentence-transformers
Requires-Dist: onnx
Requires-Dist: onnxruntime
Requires-Dist: optimum
